bbook_maker-1.1.0.dist-info/METADATA
bbook_maker-1.1.0.dist-info/WHEEL
bbook_maker-1.1.0.dist-info/entry_points.txt
bbook_maker-1.1.0.dist-info/licenses/LICENSE
book_maker/__init__.py
book_maker/__main__.py
book_maker/cli.py
book_maker/config.py
book_maker/loader/__init__.py
book_maker/loader/base_loader.py
book_maker/loader/epub_loader.py
book_maker/loader/helper.py
book_maker/loader/md_loader.py
book_maker/loader/srt_loader.py
book_maker/loader/txt_loader.py
book_maker/obok.py
book_maker/translator/__init__.py
book_maker/translator/base_translator.py
book_maker/translator/caiyun_translator.py
book_maker/translator/chatgptapi_translator.py
book_maker/translator/claude_translator.py
book_maker/translator/custom_api_translator.py
book_maker/translator/deepl_free_translator.py
book_maker/translator/deepl_translator.py
book_maker/translator/gemini_translator.py
book_maker/translator/google_translator.py
book_maker/translator/groq_translator.py
book_maker/translator/litellm_translator.py
book_maker/translator/qwen_translator.py
book_maker/translator/tencent_transmart_translator.py
book_maker/translator/xai_translator.py
book_maker/utils.py
bbook_maker-1.1.0.dist-info/RECORD
