Metadata-Version: 2.1
Name: bbook-maker
Version: 1.1.0
Summary: The bilingual_book_maker is an AI translation tool that uses ChatGPT to assist users in creating multi-language versions of epub/txt files and books.
Author-Email: yihong0618 <zouzou0208@gmail.com>
License: MIT
Classifier: License :: OSI Approved :: MIT License
Classifier: Operating System :: OS Independent
Classifier: Programming Language :: Python :: 3
Project-URL: Homepage, https://github.com/yihong0618/bilingual_book_maker
Requires-Python: >=3.10
Requires-Dist: anthropic
Requires-Dist: backoff
Requires-Dist: bs4
Requires-Dist: ebooklib
Requires-Dist: google-generativeai
Requires-Dist: langdetect
Requires-Dist: litellm
Requires-Dist: openai>=1.1.1
Requires-Dist: PyDeepLX
Requires-Dist: requests
Requires-Dist: rich
Requires-Dist: tiktoken
Requires-Dist: tqdm
Requires-Dist: groq>=0.5.0
Requires-Dist: promptdown>=0.9.0
